mkdocs_pymdownx_material_extras/__init__.py
mkdocs_pymdownx_material_extras/__meta__.py
mkdocs_pymdownx_material_extras/theme/main.html
mkdocs_pymdownx_material_extras/theme/assets/pymdownx-extras/extra-c6ab11540a.css
mkdocs_pymdownx_material_extras/theme/assets/pymdownx-extras/extra-loader-B5CKpNQx.js
mkdocs_pymdownx_material_extras/theme/assets/pymdownx-extras/material-extra-3rdparty-BUCF4rjN.js
mkdocs_pymdownx_material_extras/theme/assets/pymdownx-extras/material-extra-theme-2ek1P7jT.js
mkdocs_pymdownx_material_extras/theme/partials/footer.html
mkdocs_pymdownx_material_extras/theme/partials/header.html
mkdocs_pymdownx_material_extras/theme/partials/libs.html
mkdocs_pymdownx_material_extras-2.8.dist-info/METADATA
mkdocs_pymdownx_material_extras-2.8.dist-info/WHEEL
mkdocs_pymdownx_material_extras-2.8.dist-info/entry_points.txt
mkdocs_pymdownx_material_extras-2.8.dist-info/licenses/LICENSE.md
mkdocs_pymdownx_material_extras-2.8.dist-info/RECORD
